Metadata-Version: 1.0
Name: check-palindrome-PS
Version: 0.0.3
Summary: This is palindrome checking function
Home-page: https://balajibetadur.github.io
Author: Prakash Shelar
Author-email: UNKNOWN
License: MIT
Keywords: palindrome,Python palindrome
Platform: UNKNOWN
